txtinstruct/__init__.py
txtinstruct/data.py
txtinstruct/models/__init__.py
txtinstruct/models/bashsql.py
txtinstruct/models/instructor.py
txtinstruct/models/statement.py
txtinstruct/models/txtsql.py
txtinstruct-0.1.0.dist-info/LICENSE
txtinstruct-0.1.0.dist-info/METADATA
txtinstruct-0.1.0.dist-info/WHEEL
txtinstruct-0.1.0.dist-info/top_level.txt
txtinstruct-0.1.0.dist-info/RECORD
