Metadata-Version: 2.1
Name: txtinstruct
Version: 0.1.0
Summary: Datasets and models for instruction-tuning
Home-page: https://github.com/neuml/txtinstruct
Author: NeuML
License: Apache 2.0: http://www.apache.org/licenses/LICENSE-2.0
Project-URL: Documentation, https://github.com/neuml/txtinstruct
Project-URL: Issue Tracker, https://github.com/neuml/txtinstruct/issues
Project-URL: Source Code, https://github.com/neuml/txtinstruct
Keywords: search embedding machine-learning nlp
Platform: UNKNOWN
Classifier: License :: OSI Approved :: Apache Software License
Classifier: Operating System :: OS Independent
Classifier: Programming Language :: Python :: 3
Classifier: Topic :: Scientific/Engineering :: Artificial Intelligence
Classifier: Topic :: Software Development
Classifier: Topic :: Text Processing :: Indexing
Classifier: Topic :: Utilities
Requires-Python: >=3.7
Requires-Dist: datasets (>=2.8.0)
Requires-Dist: tqdm (>=4.48.0)
Requires-Dist: txtai (>=5.5.0)
